MANIFEST.in
README.md
setup.py
pyinkscape/__init__.py
pyinkscape/__version__.py
pyinkscape/charts.py
pyinkscape/inkscape.py
pyinkscape/render.py
pyinkscape/styles.py
pyinkscape.egg-info/PKG-INFO
pyinkscape.egg-info/SOURCES.txt
pyinkscape.egg-info/dependency_links.txt
pyinkscape.egg-info/requires.txt
pyinkscape.egg-info/top_level.txt
pyinkscape/data/blank.svg
test/test_pyinkscape.py
test/data/canvas-0.92.4.svg
test/data/graphic.svg