Metadata-Version: 2.1
Name: pyinkscape
Version: 0.1a3
Summary: A library to manipulate Inkscape SVG content using Python 3
Home-page: https://github.com/letuananh/pyinkscape
Author: Le Tuan Anh
Author-email: tuananh.ke@gmail.com
License: MIT License
Project-URL: Bug Tracker, https://github.com/letuananh/pyinkscape/issues
Project-URL: Source Code, https://github.com/letuananh/pyinkscape/
Keywords: python3 inkscape svg
Platform: any
Classifier: Programming Language :: Python
Classifier: Development Status :: 2 - Pre-Alpha
Classifier: Intended Audience :: Developers
Classifier: License :: OSI Approved :: MIT License
Classifier: Operating System :: OS Independent
Classifier: Topic :: Multimedia :: Graphics
Classifier: Topic :: Multimedia :: Graphics :: Editors :: Vector-Based
Classifier: Topic :: Software Development :: Libraries :: Python Modules
Provides-Extra: dev
